rq_win/__init__.py
rq_win/worker.py
rq_win-0.4.1.dist-info/licenses/LICENSE
rq_win-0.4.1.dist-info/METADATA
rq_win-0.4.1.dist-info/WHEEL
rq_win-0.4.1.dist-info/top_level.txt
rq_win-0.4.1.dist-info/RECORD
