Metadata-Version: 2.4
Name: rq-win
Version: 0.4.1
Summary: RQ Worker class that works for development on Windows
Home-page: https://github.com/michaelbrooks/rq-win
Author: Michael Brooks
Author-email: mjbrooks@uw.edu
License: MIT
Keywords: rq queue windows
Classifier: Development Status :: 3 - Alpha
Classifier: Topic :: Utilities
Classifier: License :: OSI Approved :: MIT License
License-File: LICENSE
Requires-Dist: rq>1.8.1
Requires-Dist: times
Dynamic: author
Dynamic: author-email
Dynamic: classifier
Dynamic: description
Dynamic: description-content-type
Dynamic: home-page
Dynamic: keywords
Dynamic: license
Dynamic: license-file
Dynamic: requires-dist
Dynamic: summary
